iyaml/__init__.py
iyaml/__main__.py
iyaml/iyaml.py
iyaml-0.1.2.dist-info/LICENSE
iyaml-0.1.2.dist-info/METADATA
iyaml-0.1.2.dist-info/NOTICE
iyaml-0.1.2.dist-info/WHEEL
iyaml-0.1.2.dist-info/top_level.txt
iyaml-0.1.2.dist-info/RECORD
