Metadata-Version: 2.1
Name: iyaml
Version: 0.1.2
Summary: YAML macro processor
Home-page: https://github.com/andmeln/iyaml/
Author: Andrey Melnikov
Author-email: andmeln@hotmail.com
License: Apache License, Version 2.0
Requires-Python: >=3.7
License-File: LICENSE
License-File: NOTICE
Requires-Dist: PyYAML
